textmancy/__init__.py
textmancy/components/__init__.py
textmancy/components/annotator.py
textmancy/components/consolidator.py
textmancy/components/extractor.py
textmancy/components/processor.py
textmancy/components/segmentor.py
textmancy/targets.py
textmancy/utils.py
textmancy-0.3.0.dist-info/LICENSE
textmancy-0.3.0.dist-info/METADATA
textmancy-0.3.0.dist-info/WHEEL
textmancy-0.3.0.dist-info/RECORD
